_expresso.so
expresso/__init__.py
expresso/evaluator.py
expresso/expression.py
expresso/printer.py
expresso/visitor.py
expresso/pycas/__init__.py
expresso/pycas/algorithms.py
expresso/pycas/codeprinter.py
expresso/pycas/core.py
expresso/pycas/expression.py
expresso/pycas/functions.py
expresso/pycas/printer.py
expresso/pycas/compilers/__init__.py
expresso/pycas/compilers/c_compiler.py
expresso/pycas/compilers/lambda_compiler.py
expresso/pycas/compilers/numpy_compiler.py
expresso/pycas/evaluators/__init__.py
expresso/pycas/evaluators/canonical_form.py
expresso/pycas/evaluators/expand_evaluator.py
expresso/pycas/evaluators/logic_evaluator.py
expresso/pycas/evaluators/main_evaluator.py
expresso/pycas/evaluators/numeric_evaluator.py
expresso/pycas/evaluators/optimizers.py
expresso/pycas/evaluators/rule_symbols.py
expresso/pycas/evaluators/type_evaluator.py
expresso/tests/__init__.py
expresso/tests/test_expresso.py
expresso/tests/test_pycas.py
expresso-0.1.5.dist-info/DESCRIPTION.rst
expresso-0.1.5.dist-info/METADATA
expresso-0.1.5.dist-info/RECORD
expresso-0.1.5.dist-info/WHEEL
expresso-0.1.5.dist-info/metadata.json
expresso-0.1.5.dist-info/top_level.txt
