Metadata-Version: 2.0
Name: expresso
Version: 0.1.5
Summary: A symbolic expression manipulation library.
Home-page: https://github.com/TheLartians/Expresso
Author: Lars Melchior
Author-email: thelartians@gmail.com
License: MIT
Keywords: expression symbolic manipulation algebra
Platform: UNKNOWN
Classifier: Development Status :: 4 - Beta
Classifier: License :: OSI Approved :: MIT License
Classifier: Programming Language :: Python :: 2.7
Provides-Extra: pycas
Requires-Dist: mpmath; extra == 'pycas'
Requires-Dist: numpy; extra == 'pycas'
